patchcommander/__init__.py
patchcommander/cli.py
patchcommander/config_ui.py
patchcommander/diff_viewer.py
patchcommander/api/__init__.py
patchcommander/api/finder.py
patchcommander/api/manipulator.py
patchcommander/api/processor.py
patchcommander/core/__init__.py
patchcommander/core/config.py
patchcommander/core/console.py
patchcommander/core/interfaces.py
patchcommander/core/languages.py
patchcommander/core/nodes.py
patchcommander/core/text_utils.py
patchcommander/core/trees.py
patchcommander/core/finder/__init__.py
patchcommander/core/finder/base.py
patchcommander/core/finder/factory.py
patchcommander/core/finder/python_code_finder.py
patchcommander/core/finder/typescript_code_finder.py
patchcommander/core/manipulator/__init__.py
patchcommander/core/manipulator/abstract.py
patchcommander/core/manipulator/base.py
patchcommander/core/manipulator/python_manipulator.py
patchcommander/core/manipulator/typescript_manipulator.py
patchcommander/core/pipeline/__init__.py
patchcommander/core/pipeline/models.py
patchcommander/core/pipeline/pipeline.py
patchcommander/core/pipeline/processor_base.py
patchcommander/core/pipeline/post_processors/__init__.py
patchcommander/core/pipeline/post_processors/duplicate_checker.py
patchcommander/core/pipeline/post_processors/syntax_validator.py
patchcommander/core/pipeline/pre_processors/__init__.py
patchcommander/core/pipeline/pre_processors/global_processor.py
patchcommander/core/pipeline/pre_processors/custom/__init__.py
patchcommander/core/pipeline/pre_processors/custom/markdown_code_block_cleaner.py
patchcommander/core/pipeline/pre_processors/custom/method_splitter.py
patchcommander/core/pipeline/pre_processors/custom/xpath_analyzer.py
patchcommander/core/pipeline/pre_processors/custom/xpath_method_corrector.py
patchcommander/core/pipeline/processors/__init__.py
patchcommander/core/pipeline/processors/base_manipulator_processor.py
patchcommander/core/pipeline/processors/decorator.py
patchcommander-1.2.1.dist-info/LICENSE
patchcommander-1.2.1.dist-info/METADATA
patchcommander-1.2.1.dist-info/WHEEL
patchcommander-1.2.1.dist-info/entry_points.txt
patchcommander-1.2.1.dist-info/top_level.txt
patchcommander-1.2.1.dist-info/RECORD
