Metadata-Version: 2.2
Name: patchcommander
Version: 1.2.1
Summary: AI-assisted coding automation tool for streamlined LLM code integration
Author: PatchCommander Team
Author-email: jacekjursza <jacek.jursza@gmail.com>
License: MIT License
Project-URL: Homepage, https://github.com/jacekjursza/PatchCommander
Project-URL: Bug Tracker, https://github.com/jacekjursza/PatchCommander/issues
Keywords: ai,development,code-generation,llm,automation
Classifier: Programming Language :: Python :: 3
Classifier: License :: OSI Approved :: MIT License
Classifier: Operating System :: OS Independent
Classifier: Topic :: Software Development :: Code Generators
Classifier: Topic :: Software Development :: Libraries :: Python Modules
Classifier: Intended Audience :: Developers
Requires-Python: >=3.8
License-File: LICENSE
Requires-Dist: rich>=12.6.0
Requires-Dist: pyperclip>=1.8.2
Requires-Dist: tree-sitter>=0.20.0
Requires-Dist: tree-sitter-python>=0.20.0
Requires-Dist: tree-sitter-javascript>=0.20.0
Requires-Dist: tree-sitter-typescript==0.23.2
Requires-Dist: diff-match-patch>=20200713
Requires-Dist: textual>=0.14.0
Dynamic: author
Dynamic: requires-python
